{"dependencies":[{"name":"C:\\Users\\kea_h\\Desktop\\vrandblog\\node_modules\\bootstrap-vue\\package.json","includedInParent":true,"mtime":1521249090354}],"generated":{"js":"'use strict';\n\nObject.defineProperty(exports, \"__esModule\", {\n  value: true\n});\n// Polyfills for SSR\n\nvar isSSR = typeof window === 'undefined';\n\nvar HTMLElement = exports.HTMLElement = isSSR ? Object : window.HTMLElement;","map":{"mappings":[{"generated":{"line":6,"column":0},"source":"vrandblog\\node_modules\\bootstrap-vue\\es\\utils\\ssr.js","original":{"line":1,"column":0}},{"generated":{"line":8,"column":0},"source":"vrandblog\\node_modules\\bootstrap-vue\\es\\utils\\ssr.js","original":{"line":3,"column":0}},{"name":"isSSR","generated":{"line":8,"column":4},"source":"vrandblog\\node_modules\\bootstrap-vue\\es\\utils\\ssr.js","original":{"line":3,"column":4}},{"generated":{"line":8,"column":12},"source":"vrandblog\\node_modules\\bootstrap-vue\\es\\utils\\ssr.js","original":{"line":3,"column":12}},{"name":"window","generated":{"line":8,"column":19},"source":"vrandblog\\node_modules\\bootstrap-vue\\es\\utils\\ssr.js","original":{"line":3,"column":19}},{"generated":{"line":8,"column":25},"source":"vrandblog\\node_modules\\bootstrap-vue\\es\\utils\\ssr.js","original":{"line":3,"column":12}},{"generated":{"line":8,"column":30},"source":"vrandblog\\node_modules\\bootstrap-vue\\es\\utils\\ssr.js","original":{"line":3,"column":30}},{"generated":{"line":8,"column":41},"source":"vrandblog\\node_modules\\bootstrap-vue\\es\\utils\\ssr.js","original":{"line":3,"column":0}},{"generated":{"line":10,"column":0},"source":"vrandblog\\node_modules\\bootstrap-vue\\es\\utils\\ssr.js","original":{"line":5,"column":7}},{"name":"HTMLElement","generated":{"line":10,"column":4},"source":"vrandblog\\node_modules\\bootstrap-vue\\es\\utils\\ssr.js","original":{"line":5,"column":11}},{"name":"isSSR","generated":{"line":10,"column":40},"source":"vrandblog\\node_modules\\bootstrap-vue\\es\\utils\\ssr.js","original":{"line":5,"column":25}},{"name":"Object","generated":{"line":10,"column":48},"source":"vrandblog\\node_modules\\bootstrap-vue\\es\\utils\\ssr.js","original":{"line":5,"column":33}},{"generated":{"line":10,"column":54},"source":"vrandblog\\node_modules\\bootstrap-vue\\es\\utils\\ssr.js","original":{"line":5,"column":25}},{"name":"window","generated":{"line":10,"column":57},"source":"vrandblog\\node_modules\\bootstrap-vue\\es\\utils\\ssr.js","original":{"line":5,"column":42}},{"name":"HTMLElement","generated":{"line":10,"column":64},"source":"vrandblog\\node_modules\\bootstrap-vue\\es\\utils\\ssr.js","original":{"line":5,"column":49}},{"generated":{"line":10,"column":75},"source":"vrandblog\\node_modules\\bootstrap-vue\\es\\utils\\ssr.js","original":{"line":5,"column":7}}],"sources":{"vrandblog\\node_modules\\bootstrap-vue\\es\\utils\\ssr.js":"// Polyfills for SSR\n\nvar isSSR = typeof window === 'undefined';\n\nexport var HTMLElement = isSSR ? Object : window.HTMLElement;"},"lineCount":null}},"hash":"3ebbfdf6847d820823187f9b980dca23","cacheData":{"env":{}}}