{"dependencies":[{"name":"C:\\Users\\kea_h\\vrandblog\\package.json","includedInParent":true,"mtime":1521988836233},{"name":"C:\\Users\\kea_h\\vrandblog\\.babelrc","includedInParent":true,"mtime":1521988825970},{"name":"C:\\Users\\kea_h\\vrandblog\\node_modules\\sshpk\\package.json","includedInParent":true,"mtime":1521988835387},{"name":"assert-plus","loc":{"line":8,"column":21}},{"name":"../key","loc":{"line":9,"column":18}},{"name":"../private-key","loc":{"line":10,"column":25}},{"name":"../utils","loc":{"line":11,"column":20}},{"name":"../ssh-buffer","loc":{"line":12,"column":24}},{"name":"../dhe","loc":{"line":13,"column":18}},{"name":"buffer"}],"generated":{"js":"var Buffer = require(\"buffer\").Buffer;\n// Copyright 2017 Joyent, Inc.\r\n\r\nmodule.exports = {\r\n\tread: read,\r\n\twrite: write\r\n};\r\n\r\nvar assert = require('assert-plus');\r\nvar Key = require('../key');\r\nvar PrivateKey = require('../private-key');\r\nvar utils = require('../utils');\r\nvar SSHBuffer = require('../ssh-buffer');\r\nvar Dhe = require('../dhe');\r\n\r\nvar supportedAlgos = {\r\n\t'rsa-sha1' : 5,\r\n\t'rsa-sha256' : 8,\r\n\t'rsa-sha512' : 10,\r\n\t'ecdsa-p256-sha256' : 13,\r\n\t'ecdsa-p384-sha384' : 14\r\n\t/*\r\n\t * ed25519 is hypothetically supported with id 15\r\n\t * but the common tools available don't appear to be\r\n\t * capable of generating/using ed25519 keys\r\n\t */\r\n};\r\n\r\nvar supportedAlgosById = {};\r\nObject.keys(supportedAlgos).forEach(function (k) {\r\n\tsupportedAlgosById[supportedAlgos[k]] = k.toUpperCase();\r\n});\r\n\r\nfunction read(buf, options) {\r\n\tif (typeof (buf) !== 'string') {\r\n\t\tassert.buffer(buf, 'buf');\r\n\t\tbuf = buf.toString('ascii');\r\n\t}\r\n\tvar lines = buf.split('\\n');\r\n\tif (lines[0].match(/^Private-key-format\\: v1/)) {\r\n\t\tvar algElems = lines[1].split(' ');\r\n\t\tvar algoNum = parseInt(algElems[1], 10);\r\n\t\tvar algoName = algElems[2];\r\n\t\tif (!supportedAlgosById[algoNum])\r\n\t\t\tthrow (new Error('Unsupported algorithm: ' + algoName));\r\n\t\treturn (readDNSSECPrivateKey(algoNum, lines.slice(2)));\r\n\t}\r\n\r\n\t// skip any comment-lines\r\n\tvar line = 0;\r\n\t/* JSSTYLED */\r\n\twhile (lines[line].match(/^\\;/))\r\n\t\tline++;\r\n\t// we should now have *one single* line left with our KEY on it.\r\n\tif ((lines[line].match(/\\. IN KEY /) ||\r\n\t    lines[line].match(/\\. IN DNSKEY /)) && lines[line+1].length === 0) {\r\n\t\treturn (readRFC3110(lines[line]));\r\n\t}\r\n\tthrow (new Error('Cannot parse dnssec key'));\r\n}\r\n\r\nfunction readRFC3110(keyString) {\r\n\tvar elems = keyString.split(' ');\r\n\t//unused var flags = parseInt(elems[3], 10);\r\n\t//unused var protocol = parseInt(elems[4], 10);\r\n\tvar algorithm = parseInt(elems[5], 10);\r\n\tif (!supportedAlgosById[algorithm])\r\n\t\tthrow (new Error('Unsupported algorithm: ' + algorithm));\r\n\tvar base64key = elems.slice(6, elems.length).join();\r\n\tvar keyBuffer = new Buffer(base64key, 'base64');\r\n\tif (supportedAlgosById[algorithm].match(/^RSA-/)) {\r\n\t\t// join the rest of the body into a single base64-blob\r\n\t\tvar publicExponentLen = keyBuffer.readUInt8(0);\r\n\t\tif (publicExponentLen != 3 && publicExponentLen != 1)\r\n\t\t\tthrow (new Error('Cannot parse dnssec key: ' +\r\n\t\t\t    'unsupported exponent length'));\r\n\r\n\t\tvar publicExponent = keyBuffer.slice(1, publicExponentLen+1);\r\n\t\tpublicExponent = utils.mpNormalize(publicExponent);\r\n\t\tvar modulus = keyBuffer.slice(1+publicExponentLen);\r\n\t\tmodulus = utils.mpNormalize(modulus);\r\n\t\t// now, make the key\r\n\t\tvar rsaKey = {\r\n\t\t\ttype: 'rsa',\r\n\t\t\tparts: []\r\n\t\t};\r\n\t\trsaKey.parts.push({ name: 'e', data: publicExponent});\r\n\t\trsaKey.parts.push({ name: 'n', data: modulus});\r\n\t\treturn (new Key(rsaKey));\r\n\t}\r\n\tif (supportedAlgosById[algorithm] === 'ECDSA-P384-SHA384' ||\r\n\t    supportedAlgosById[algorithm] === 'ECDSA-P256-SHA256') {\r\n\t\tvar curve = 'nistp384';\r\n\t\tvar size = 384;\r\n\t\tif (supportedAlgosById[algorithm].match(/^ECDSA-P256-SHA256/)) {\r\n\t\t\tcurve = 'nistp256';\r\n\t\t\tsize = 256;\r\n\t\t}\r\n\r\n\t\tvar ecdsaKey = {\r\n\t\t\ttype: 'ecdsa',\r\n\t\t\tcurve: curve,\r\n\t\t\tsize: size,\r\n\t\t\tparts: [\r\n\t\t\t\t{name: 'curve', data: new Buffer(curve) },\r\n\t\t\t\t{name: 'Q', data: utils.ecNormalize(keyBuffer) }\r\n\t\t\t]\r\n\t\t};\r\n\t\treturn (new Key(ecdsaKey));\r\n\t}\r\n\tthrow (new Error('Unsupported algorithm: ' +\r\n\t    supportedAlgosById[algorithm]));\r\n}\r\n\r\nfunction elementToBuf(e) {\r\n\treturn (new Buffer(e.split(' ')[1], 'base64'));\r\n}\r\n\r\nfunction readDNSSECRSAPrivateKey(elements) {\r\n\tvar rsaParams = {};\r\n\telements.forEach(function (element) {\r\n\t\tif (element.split(' ')[0] === 'Modulus:')\r\n\t\t\trsaParams['n'] = elementToBuf(element);\r\n\t\telse if (element.split(' ')[0] === 'PublicExponent:')\r\n\t\t\trsaParams['e'] = elementToBuf(element);\r\n\t\telse if (element.split(' ')[0] === 'PrivateExponent:')\r\n\t\t\trsaParams['d'] = elementToBuf(element);\r\n\t\telse if (element.split(' ')[0] === 'Prime1:')\r\n\t\t\trsaParams['p'] = elementToBuf(element);\r\n\t\telse if (element.split(' ')[0] === 'Prime2:')\r\n\t\t\trsaParams['q'] = elementToBuf(element);\r\n\t\telse if (element.split(' ')[0] === 'Exponent1:')\r\n\t\t\trsaParams['dmodp'] = elementToBuf(element);\r\n\t\telse if (element.split(' ')[0] === 'Exponent2:')\r\n\t\t\trsaParams['dmodq'] = elementToBuf(element);\r\n\t\telse if (element.split(' ')[0] === 'Coefficient:')\r\n\t\t\trsaParams['iqmp'] = elementToBuf(element);\r\n\t});\r\n\t// now, make the key\r\n\tvar key = {\r\n\t\ttype: 'rsa',\r\n\t\tparts: [\r\n\t\t\t{ name: 'e', data: utils.mpNormalize(rsaParams['e'])},\r\n\t\t\t{ name: 'n', data: utils.mpNormalize(rsaParams['n'])},\r\n\t\t\t{ name: 'd', data: utils.mpNormalize(rsaParams['d'])},\r\n\t\t\t{ name: 'p', data: utils.mpNormalize(rsaParams['p'])},\r\n\t\t\t{ name: 'q', data: utils.mpNormalize(rsaParams['q'])},\r\n\t\t\t{ name: 'dmodp',\r\n\t\t\t    data: utils.mpNormalize(rsaParams['dmodp'])},\r\n\t\t\t{ name: 'dmodq',\r\n\t\t\t    data: utils.mpNormalize(rsaParams['dmodq'])},\r\n\t\t\t{ name: 'iqmp',\r\n\t\t\t    data: utils.mpNormalize(rsaParams['iqmp'])}\r\n\t\t]\r\n\t};\r\n\treturn (new PrivateKey(key));\r\n}\r\n\r\nfunction readDNSSECPrivateKey(alg, elements) {\r\n\tif (supportedAlgosById[alg].match(/^RSA-/)) {\r\n\t\treturn (readDNSSECRSAPrivateKey(elements));\r\n\t}\r\n\tif (supportedAlgosById[alg] === 'ECDSA-P384-SHA384' ||\r\n\t    supportedAlgosById[alg] === 'ECDSA-P256-SHA256') {\r\n\t\tvar d = new Buffer(elements[0].split(' ')[1], 'base64');\r\n\t\tvar curve = 'nistp384';\r\n\t\tvar size = 384;\r\n\t\tif (supportedAlgosById[alg] === 'ECDSA-P256-SHA256') {\r\n\t\t\tcurve = 'nistp256';\r\n\t\t\tsize = 256;\r\n\t\t}\r\n\t\t// DNSSEC generates the public-key on the fly (go calculate it)\r\n\t\tvar publicKey = utils.publicFromPrivateECDSA(curve, d);\r\n\t\tvar Q = publicKey.part['Q'].data;\r\n\t\tvar ecdsaKey = {\r\n\t\t\ttype: 'ecdsa',\r\n\t\t\tcurve: curve,\r\n\t\t\tsize: size,\r\n\t\t\tparts: [\r\n\t\t\t\t{name: 'curve', data: new Buffer(curve) },\r\n\t\t\t\t{name: 'd', data: d },\r\n\t\t\t\t{name: 'Q', data: Q }\r\n\t\t\t]\r\n\t\t};\r\n\t\treturn (new PrivateKey(ecdsaKey));\r\n\t}\r\n\tthrow (new Error('Unsupported algorithm: ' + supportedAlgosById[alg]));\r\n}\r\n\r\nfunction dnssecTimestamp(date) {\r\n\tvar year = date.getFullYear() + ''; //stringify\r\n\tvar month = (date.getMonth() + 1);\r\n\tvar timestampStr = year + month + date.getUTCDate();\r\n\ttimestampStr += '' + date.getUTCHours() + date.getUTCMinutes();\r\n\ttimestampStr += date.getUTCSeconds();\r\n\treturn (timestampStr);\r\n}\r\n\r\nfunction rsaAlgFromOptions(opts) {\r\n\tif (!opts || !opts.hashAlgo || opts.hashAlgo === 'sha1')\r\n\t\treturn ('5 (RSASHA1)');\r\n\telse if (opts.hashAlgo === 'sha256')\r\n\t\treturn ('8 (RSASHA256)');\r\n\telse if (opts.hashAlgo === 'sha512')\r\n\t\treturn ('10 (RSASHA512)');\r\n\telse\r\n\t\tthrow (new Error('Unknown or unsupported hash: ' +\r\n\t\t    opts.hashAlgo));\r\n}\r\n\r\nfunction writeRSA(key, options) {\r\n\t// if we're missing parts, add them.\r\n\tif (!key.part.dmodp || !key.part.dmodq) {\r\n\t\tutils.addRSAMissing(key);\r\n\t}\r\n\r\n\tvar out = '';\r\n\tout += 'Private-key-format: v1.3\\n';\r\n\tout += 'Algorithm: ' + rsaAlgFromOptions(options) + '\\n';\r\n\tvar n = utils.mpDenormalize(key.part['n'].data);\r\n\tout += 'Modulus: ' + n.toString('base64') + '\\n';\r\n\tvar e = utils.mpDenormalize(key.part['e'].data);\r\n\tout += 'PublicExponent: ' + e.toString('base64') + '\\n';\r\n\tvar d = utils.mpDenormalize(key.part['d'].data);\r\n\tout += 'PrivateExponent: ' + d.toString('base64') + '\\n';\r\n\tvar p = utils.mpDenormalize(key.part['p'].data);\r\n\tout += 'Prime1: ' + p.toString('base64') + '\\n';\r\n\tvar q = utils.mpDenormalize(key.part['q'].data);\r\n\tout += 'Prime2: ' + q.toString('base64') + '\\n';\r\n\tvar dmodp = utils.mpDenormalize(key.part['dmodp'].data);\r\n\tout += 'Exponent1: ' + dmodp.toString('base64') + '\\n';\r\n\tvar dmodq = utils.mpDenormalize(key.part['dmodq'].data);\r\n\tout += 'Exponent2: ' + dmodq.toString('base64') + '\\n';\r\n\tvar iqmp = utils.mpDenormalize(key.part['iqmp'].data);\r\n\tout += 'Coefficient: ' + iqmp.toString('base64') + '\\n';\r\n\t// Assume that we're valid as-of now\r\n\tvar timestamp = new Date();\r\n\tout += 'Created: ' + dnssecTimestamp(timestamp) + '\\n';\r\n\tout += 'Publish: ' + dnssecTimestamp(timestamp) + '\\n';\r\n\tout += 'Activate: ' + dnssecTimestamp(timestamp) + '\\n';\r\n\treturn (new Buffer(out, 'ascii'));\r\n}\r\n\r\nfunction writeECDSA(key, options) {\r\n\tvar out = '';\r\n\tout += 'Private-key-format: v1.3\\n';\r\n\r\n\tif (key.curve === 'nistp256') {\r\n\t\tout += 'Algorithm: 13 (ECDSAP256SHA256)\\n';\r\n\t} else if (key.curve === 'nistp384') {\r\n\t\tout += 'Algorithm: 14 (ECDSAP384SHA384)\\n';\r\n\t} else {\r\n\t\tthrow (new Error('Unsupported curve'));\r\n\t}\r\n\tvar base64Key = key.part['d'].data.toString('base64');\r\n\tout += 'PrivateKey: ' + base64Key + '\\n';\r\n\r\n\t// Assume that we're valid as-of now\r\n\tvar timestamp = new Date();\r\n\tout += 'Created: ' + dnssecTimestamp(timestamp) + '\\n';\r\n\tout += 'Publish: ' + dnssecTimestamp(timestamp) + '\\n';\r\n\tout += 'Activate: ' + dnssecTimestamp(timestamp) + '\\n';\r\n\r\n\treturn (new Buffer(out, 'ascii'));\r\n}\r\n\r\nfunction write(key, options) {\r\n\tif (PrivateKey.isPrivateKey(key)) {\r\n\t\tif (key.type === 'rsa') {\r\n\t\t\treturn (writeRSA(key, options));\r\n\t\t} else if (key.type === 'ecdsa') {\r\n\t\t\treturn (writeECDSA(key, options));\r\n\t\t} else {\r\n\t\t\tthrow (new Error('Unsupported algorithm: ' + key.type));\r\n\t\t}\r\n\t} else if (Key.isKey(key)) {\r\n\t\t/*\r\n\t\t * RFC3110 requires a keyname, and a keytype, which we\r\n\t\t * don't really have a mechanism for specifying such\r\n\t\t * additional metadata.\r\n\t\t */\r\n\t\tthrow (new Error('Format \"dnssec\" only supports ' +\r\n\t\t    'writing private keys'));\r\n\t} else {\r\n\t\tthrow (new Error('key is not a Key or PrivateKey'));\r\n\t}\r\n}\r\n","map":{"mappings":[{"source":"node_modules\\sshpk\\lib\\formats\\dnssec.js","original":{"line":1,"column":0},"generated":{"line":2,"column":0}},{"source":"node_modules\\sshpk\\lib\\formats\\dnssec.js","original":{"line":2,"column":0},"generated":{"line":3,"column":0}},{"source":"node_modules\\sshpk\\lib\\formats\\dnssec.js","original":{"line":3,"column":0},"generated":{"line":4,"column":0}},{"source":"node_modules\\sshpk\\lib\\formats\\dnssec.js","original":{"line":4,"column":0},"generated":{"line":5,"column":0}},{"source":"node_modules\\sshpk\\lib\\formats\\dnssec.js","original":{"line":5,"column":0},"generated":{"line":6,"column":0}},{"source":"node_modules\\sshpk\\lib\\formats\\dnssec.js","original":{"line":6,"column":0},"generated":{"line":7,"column":0}},{"source":"node_modules\\sshpk\\lib\\formats\\dnssec.js","original":{"line":7,"column":0},"generated":{"line":8,"column":0}},{"source":"node_modules\\sshpk\\lib\\formats\\dnssec.js","original":{"line":8,"column":0},"generated":{"line":9,"column":0}},{"source":"node_modules\\sshpk\\lib\\formats\\dnssec.js","original":{"line":9,"column":0},"generated":{"line":10,"column":0}},{"source":"node_modules\\sshpk\\lib\\formats\\dnssec.js","original":{"line":10,"column":0},"generated":{"line":11,"column":0}},{"source":"node_modules\\sshpk\\lib\\formats\\dnssec.js","original":{"line":11,"column":0},"generated":{"line":12,"column":0}},{"source":"node_modules\\sshpk\\lib\\formats\\dnssec.js","original":{"line":12,"column":0},"generated":{"line":13,"column":0}},{"source":"node_modules\\sshpk\\lib\\formats\\dnssec.js","original":{"line":13,"column":0},"generated":{"line":14,"column":0}},{"source":"node_modules\\sshpk\\lib\\formats\\dnssec.js","original":{"line":14,"column":0},"generated":{"line":15,"column":0}},{"source":"node_modules\\sshpk\\lib\\formats\\dnssec.js","original":{"line":15,"column":0},"generated":{"line":16,"column":0}},{"source":"node_modules\\sshpk\\lib\\formats\\dnssec.js","original":{"line":16,"column":0},"generated":{"line":17,"column":0}},{"source":"node_modules\\sshpk\\lib\\formats\\dnssec.js","original":{"line":17,"column":0},"generated":{"line":18,"column":0}},{"source":"node_modules\\sshpk\\lib\\formats\\dnssec.js","original":{"line":18,"column":0},"generated":{"line":19,"column":0}},{"source":"node_modules\\sshpk\\lib\\formats\\dnssec.js","original":{"line":19,"column":0},"generated":{"line":20,"column":0}},{"source":"node_modules\\sshpk\\lib\\formats\\dnssec.js","original":{"line":20,"column":0},"generated":{"line":21,"column":0}},{"source":"node_modules\\sshpk\\lib\\formats\\dnssec.js","original":{"line":21,"column":0},"generated":{"line":22,"column":0}},{"source":"node_modules\\sshpk\\lib\\formats\\dnssec.js","original":{"line":22,"column":0},"generated":{"line":23,"column":0}},{"source":"node_modules\\sshpk\\lib\\formats\\dnssec.js","original":{"line":23,"column":0},"generated":{"line":24,"column":0}},{"source":"node_modules\\sshpk\\lib\\formats\\dnssec.js","original":{"line":24,"column":0},"generated":{"line":25,"column":0}},{"source":"node_modules\\sshpk\\lib\\formats\\dnssec.js","original":{"line":25,"column":0},"generated":{"line":26,"column":0}},{"source":"node_modules\\sshpk\\lib\\formats\\dnssec.js","original":{"line":26,"column":0},"generated":{"line":27,"column":0}},{"source":"node_modules\\sshpk\\lib\\formats\\dnssec.js","original":{"line":27,"column":0},"generated":{"line":28,"column":0}},{"source":"node_modules\\sshpk\\lib\\formats\\dnssec.js","original":{"line":28,"column":0},"generated":{"line":29,"column":0}},{"source":"node_modules\\sshpk\\lib\\formats\\dnssec.js","original":{"line":29,"column":0},"generated":{"line":30,"column":0}},{"source":"node_modules\\sshpk\\lib\\formats\\dnssec.js","original":{"line":30,"column":0},"generated":{"line":31,"column":0}},{"source":"node_modules\\sshpk\\lib\\formats\\dnssec.js","original":{"line":31,"column":0},"generated":{"line":32,"column":0}},{"source":"node_modules\\sshpk\\lib\\formats\\dnssec.js","original":{"line":32,"column":0},"generated":{"line":33,"column":0}},{"source":"node_modules\\sshpk\\lib\\formats\\dnssec.js","original":{"line":33,"column":0},"generated":{"line":34,"column":0}},{"source":"node_modules\\sshpk\\lib\\formats\\dnssec.js","original":{"line":34,"column":0},"generated":{"line":35,"column":0}},{"source":"node_modules\\sshpk\\lib\\formats\\dnssec.js","original":{"line":35,"column":0},"generated":{"line":36,"column":0}},{"source":"node_modules\\sshpk\\lib\\formats\\dnssec.js","original":{"line":36,"column":0},"generated":{"line":37,"column":0}},{"source":"node_modules\\sshpk\\lib\\formats\\dnssec.js","original":{"line":37,"column":0},"generated":{"line":38,"column":0}},{"source":"node_modules\\sshpk\\lib\\formats\\dnssec.js","original":{"line":38,"column":0},"generated":{"line":39,"column":0}},{"source":"node_modules\\sshpk\\lib\\formats\\dnssec.js","original":{"line":39,"column":0},"generated":{"line":40,"column":0}},{"source":"node_modules\\sshpk\\lib\\formats\\dnssec.js","original":{"line":40,"column":0},"generated":{"line":41,"column":0}},{"source":"node_modules\\sshpk\\lib\\formats\\dnssec.js","original":{"line":41,"column":0},"generated":{"line":42,"column":0}},{"source":"node_modules\\sshpk\\lib\\formats\\dnssec.js","original":{"line":42,"column":0},"generated":{"line":43,"column":0}},{"source":"node_modules\\sshpk\\lib\\formats\\dnssec.js","original":{"line":43,"column":0},"generated":{"line":44,"column":0}},{"source":"node_modules\\sshpk\\lib\\formats\\dnssec.js","original":{"line":44,"column":0},"generated":{"line":45,"column":0}},{"source":"node_modules\\sshpk\\lib\\formats\\dnssec.js","original":{"line":45,"column":0},"generated":{"line":46,"column":0}},{"source":"node_modules\\sshpk\\lib\\formats\\dnssec.js","original":{"line":46,"column":0},"generated":{"line":47,"column":0}},{"source":"node_modules\\sshpk\\lib\\formats\\dnssec.js","original":{"line":47,"column":0},"generated":{"line":48,"column":0}},{"source":"node_modules\\sshpk\\lib\\formats\\dnssec.js","original":{"line":48,"column":0},"generated":{"line":49,"column":0}},{"source":"node_modules\\sshpk\\lib\\formats\\dnssec.js","original":{"line":49,"column":0},"generated":{"line":50,"column":0}},{"source":"node_modules\\sshpk\\lib\\formats\\dnssec.js","original":{"line":50,"column":0},"generated":{"line":51,"column":0}},{"source":"node_modules\\sshpk\\lib\\formats\\dnssec.js","original":{"line":51,"column":0},"generated":{"line":52,"column":0}},{"source":"node_modules\\sshpk\\lib\\formats\\dnssec.js","original":{"line":52,"column":0},"generated":{"line":53,"column":0}},{"source":"node_modules\\sshpk\\lib\\formats\\dnssec.js","original":{"line":53,"column":0},"generated":{"line":54,"column":0}},{"source":"node_modules\\sshpk\\lib\\formats\\dnssec.js","original":{"line":54,"column":0},"generated":{"line":55,"column":0}},{"source":"node_modules\\sshpk\\lib\\formats\\dnssec.js","original":{"line":55,"column":0},"generated":{"line":56,"column":0}},{"source":"node_modules\\sshpk\\lib\\formats\\dnssec.js","original":{"line":56,"column":0},"generated":{"line":57,"column":0}},{"source":"node_modules\\sshpk\\lib\\formats\\dnssec.js","original":{"line":57,"column":0},"generated":{"line":58,"column":0}},{"source":"node_modules\\sshpk\\lib\\formats\\dnssec.js","original":{"line":58,"column":0},"generated":{"line":59,"column":0}},{"source":"node_modules\\sshpk\\lib\\formats\\dnssec.js","original":{"line":59,"column":0},"generated":{"line":60,"column":0}},{"source":"node_modules\\sshpk\\lib\\formats\\dnssec.js","original":{"line":60,"column":0},"generated":{"line":61,"column":0}},{"source":"node_modules\\sshpk\\lib\\formats\\dnssec.js","original":{"line":61,"column":0},"generated":{"line":62,"column":0}},{"source":"node_modules\\sshpk\\lib\\formats\\dnssec.js","original":{"line":62,"column":0},"generated":{"line":63,"column":0}},{"source":"node_modules\\sshpk\\lib\\formats\\dnssec.js","original":{"line":63,"column":0},"generated":{"line":64,"column":0}},{"source":"node_modules\\sshpk\\lib\\formats\\dnssec.js","original":{"line":64,"column":0},"generated":{"line":65,"column":0}},{"source":"node_modules\\sshpk\\lib\\formats\\dnssec.js","original":{"line":65,"column":0},"generated":{"line":66,"column":0}},{"source":"node_modules\\sshpk\\lib\\formats\\dnssec.js","original":{"line":66,"column":0},"generated":{"line":67,"column":0}},{"source":"node_modules\\sshpk\\lib\\formats\\dnssec.js","original":{"line":67,"column":0},"generated":{"line":68,"column":0}},{"source":"node_modules\\sshpk\\lib\\formats\\dnssec.js","original":{"line":68,"column":0},"generated":{"line":69,"column":0}},{"source":"node_modules\\sshpk\\lib\\formats\\dnssec.js","original":{"line":69,"column":0},"generated":{"line":70,"column":0}},{"source":"node_modules\\sshpk\\lib\\formats\\dnssec.js","original":{"line":70,"column":0},"generated":{"line":71,"column":0}},{"source":"node_modules\\sshpk\\lib\\formats\\dnssec.js","original":{"line":71,"column":0},"generated":{"line":72,"column":0}},{"source":"node_modules\\sshpk\\lib\\formats\\dnssec.js","original":{"line":72,"column":0},"generated":{"line":73,"column":0}},{"source":"node_modules\\sshpk\\lib\\formats\\dnssec.js","original":{"line":73,"column":0},"generated":{"line":74,"column":0}},{"source":"node_modules\\sshpk\\lib\\formats\\dnssec.js","original":{"line":74,"column":0},"generated":{"line":75,"column":0}},{"source":"node_modules\\sshpk\\lib\\formats\\dnssec.js","original":{"line":75,"column":0},"generated":{"line":76,"column":0}},{"source":"node_modules\\sshpk\\lib\\formats\\dnssec.js","original":{"line":76,"column":0},"generated":{"line":77,"column":0}},{"source":"node_modules\\sshpk\\lib\\formats\\dnssec.js","original":{"line":77,"column":0},"generated":{"line":78,"column":0}},{"source":"node_modules\\sshpk\\lib\\formats\\dnssec.js","original":{"line":78,"column":0},"generated":{"line":79,"column":0}},{"source":"node_modules\\sshpk\\lib\\formats\\dnssec.js","original":{"line":79,"column":0},"generated":{"line":80,"column":0}},{"source":"node_modules\\sshpk\\lib\\formats\\dnssec.js","original":{"line":80,"column":0},"generated":{"line":81,"column":0}},{"source":"node_modules\\sshpk\\lib\\formats\\dnssec.js","original":{"line":81,"column":0},"generated":{"line":82,"column":0}},{"source":"node_modules\\sshpk\\lib\\formats\\dnssec.js","original":{"line":82,"column":0},"generated":{"line":83,"column":0}},{"source":"node_modules\\sshpk\\lib\\formats\\dnssec.js","original":{"line":83,"column":0},"generated":{"line":84,"column":0}},{"source":"node_modules\\sshpk\\lib\\formats\\dnssec.js","original":{"line":84,"column":0},"generated":{"line":85,"column":0}},{"source":"node_modules\\sshpk\\lib\\formats\\dnssec.js","original":{"line":85,"column":0},"generated":{"line":86,"column":0}},{"source":"node_modules\\sshpk\\lib\\formats\\dnssec.js","original":{"line":86,"column":0},"generated":{"line":87,"column":0}},{"source":"node_modules\\sshpk\\lib\\formats\\dnssec.js","original":{"line":87,"column":0},"generated":{"line":88,"column":0}},{"source":"node_modules\\sshpk\\lib\\formats\\dnssec.js","original":{"line":88,"column":0},"generated":{"line":89,"column":0}},{"source":"node_modules\\sshpk\\lib\\formats\\dnssec.js","original":{"line":89,"column":0},"generated":{"line":90,"column":0}},{"source":"node_modules\\sshpk\\lib\\formats\\dnssec.js","original":{"line":90,"column":0},"generated":{"line":91,"column":0}},{"source":"node_modules\\sshpk\\lib\\formats\\dnssec.js","original":{"line":91,"column":0},"generated":{"line":92,"column":0}},{"source":"node_modules\\sshpk\\lib\\formats\\dnssec.js","original":{"line":92,"column":0},"generated":{"line":93,"column":0}},{"source":"node_modules\\sshpk\\lib\\formats\\dnssec.js","original":{"line":93,"column":0},"generated":{"line":94,"column":0}},{"source":"node_modules\\sshpk\\lib\\formats\\dnssec.js","original":{"line":94,"column":0},"generated":{"line":95,"column":0}},{"source":"node_modules\\sshpk\\lib\\formats\\dnssec.js","original":{"line":95,"column":0},"generated":{"line":96,"column":0}},{"source":"node_modules\\sshpk\\lib\\formats\\dnssec.js","original":{"line":96,"column":0},"generated":{"line":97,"column":0}},{"source":"node_modules\\sshpk\\lib\\formats\\dnssec.js","original":{"line":97,"column":0},"generated":{"line":98,"column":0}},{"source":"node_modules\\sshpk\\lib\\formats\\dnssec.js","original":{"line":98,"column":0},"generated":{"line":99,"column":0}},{"source":"node_modules\\sshpk\\lib\\formats\\dnssec.js","original":{"line":99,"column":0},"generated":{"line":100,"column":0}},{"source":"node_modules\\sshpk\\lib\\formats\\dnssec.js","original":{"line":100,"column":0},"generated":{"line":101,"column":0}},{"source":"node_modules\\sshpk\\lib\\formats\\dnssec.js","original":{"line":101,"column":0},"generated":{"line":102,"column":0}},{"source":"node_modules\\sshpk\\lib\\formats\\dnssec.js","original":{"line":102,"column":0},"generated":{"line":103,"column":0}},{"source":"node_modules\\sshpk\\lib\\formats\\dnssec.js","original":{"line":103,"column":0},"generated":{"line":104,"column":0}},{"source":"node_modules\\sshpk\\lib\\formats\\dnssec.js","original":{"line":104,"column":0},"generated":{"line":105,"column":0}},{"source":"node_modules\\sshpk\\lib\\formats\\dnssec.js","original":{"line":105,"column":0},"generated":{"line":106,"column":0}},{"source":"node_modules\\sshpk\\lib\\formats\\dnssec.js","original":{"line":106,"column":0},"generated":{"line":107,"column":0}},{"source":"node_modules\\sshpk\\lib\\formats\\dnssec.js","original":{"line":107,"column":0},"generated":{"line":108,"column":0}},{"source":"node_modules\\sshpk\\lib\\formats\\dnssec.js","original":{"line":108,"column":0},"generated":{"line":109,"column":0}},{"source":"node_modules\\sshpk\\lib\\formats\\dnssec.js","original":{"line":109,"column":0},"generated":{"line":110,"column":0}},{"source":"node_modules\\sshpk\\lib\\formats\\dnssec.js","original":{"line":110,"column":0},"generated":{"line":111,"column":0}},{"source":"node_modules\\sshpk\\lib\\formats\\dnssec.js","original":{"line":111,"column":0},"generated":{"line":112,"column":0}},{"source":"node_modules\\sshpk\\lib\\formats\\dnssec.js","original":{"line":112,"column":0},"generated":{"line":113,"column":0}},{"source":"node_modules\\sshpk\\lib\\formats\\dnssec.js","original":{"line":113,"column":0},"generated":{"line":114,"column":0}},{"source":"node_modules\\sshpk\\lib\\formats\\dnssec.js","original":{"line":114,"column":0},"generated":{"line":115,"column":0}},{"source":"node_modules\\sshpk\\lib\\formats\\dnssec.js","original":{"line":115,"column":0},"generated":{"line":116,"column":0}},{"source":"node_modules\\sshpk\\lib\\formats\\dnssec.js","original":{"line":116,"column":0},"generated":{"line":117,"column":0}},{"source":"node_modules\\sshpk\\lib\\formats\\dnssec.js","original":{"line":117,"column":0},"generated":{"line":118,"column":0}},{"source":"node_modules\\sshpk\\lib\\formats\\dnssec.js","original":{"line":118,"column":0},"generated":{"line":119,"column":0}},{"source":"node_modules\\sshpk\\lib\\formats\\dnssec.js","original":{"line":119,"column":0},"generated":{"line":120,"column":0}},{"source":"node_modules\\sshpk\\lib\\formats\\dnssec.js","original":{"line":120,"column":0},"generated":{"line":121,"column":0}},{"source":"node_modules\\sshpk\\lib\\formats\\dnssec.js","original":{"line":121,"column":0},"generated":{"line":122,"column":0}},{"source":"node_modules\\sshpk\\lib\\formats\\dnssec.js","original":{"line":122,"column":0},"generated":{"line":123,"column":0}},{"source":"node_modules\\sshpk\\lib\\formats\\dnssec.js","original":{"line":123,"column":0},"generated":{"line":124,"column":0}},{"source":"node_modules\\sshpk\\lib\\formats\\dnssec.js","original":{"line":124,"column":0},"generated":{"line":125,"column":0}},{"source":"node_modules\\sshpk\\lib\\formats\\dnssec.js","original":{"line":125,"column":0},"generated":{"line":126,"column":0}},{"source":"node_modules\\sshpk\\lib\\formats\\dnssec.js","original":{"line":126,"column":0},"generated":{"line":127,"column":0}},{"source":"node_modules\\sshpk\\lib\\formats\\dnssec.js","original":{"line":127,"column":0},"generated":{"line":128,"column":0}},{"source":"node_modules\\sshpk\\lib\\formats\\dnssec.js","original":{"line":128,"column":0},"generated":{"line":129,"column":0}},{"source":"node_modules\\sshpk\\lib\\formats\\dnssec.js","original":{"line":129,"column":0},"generated":{"line":130,"column":0}},{"source":"node_modules\\sshpk\\lib\\formats\\dnssec.js","original":{"line":130,"column":0},"generated":{"line":131,"column":0}},{"source":"node_modules\\sshpk\\lib\\formats\\dnssec.js","original":{"line":131,"column":0},"generated":{"line":132,"column":0}},{"source":"node_modules\\sshpk\\lib\\formats\\dnssec.js","original":{"line":132,"column":0},"generated":{"line":133,"column":0}},{"source":"node_modules\\sshpk\\lib\\formats\\dnssec.js","original":{"line":133,"column":0},"generated":{"line":134,"column":0}},{"source":"node_modules\\sshpk\\lib\\formats\\dnssec.js","original":{"line":134,"column":0},"generated":{"line":135,"column":0}},{"source":"node_modules\\sshpk\\lib\\formats\\dnssec.js","original":{"line":135,"column":0},"generated":{"line":136,"column":0}},{"source":"node_modules\\sshpk\\lib\\formats\\dnssec.js","original":{"line":136,"column":0},"generated":{"line":137,"column":0}},{"source":"node_modules\\sshpk\\lib\\formats\\dnssec.js","original":{"line":137,"column":0},"generated":{"line":138,"column":0}},{"source":"node_modules\\sshpk\\lib\\formats\\dnssec.js","original":{"line":138,"column":0},"generated":{"line":139,"column":0}},{"source":"node_modules\\sshpk\\lib\\formats\\dnssec.js","original":{"line":139,"column":0},"generated":{"line":140,"column":0}},{"source":"node_modules\\sshpk\\lib\\formats\\dnssec.js","original":{"line":140,"column":0},"generated":{"line":141,"column":0}},{"source":"node_modules\\sshpk\\lib\\formats\\dnssec.js","original":{"line":141,"column":0},"generated":{"line":142,"column":0}},{"source":"node_modules\\sshpk\\lib\\formats\\dnssec.js","original":{"line":142,"column":0},"generated":{"line":143,"column":0}},{"source":"node_modules\\sshpk\\lib\\formats\\dnssec.js","original":{"line":143,"column":0},"generated":{"line":144,"column":0}},{"source":"node_modules\\sshpk\\lib\\formats\\dnssec.js","original":{"line":144,"column":0},"generated":{"line":145,"column":0}},{"source":"node_modules\\sshpk\\lib\\formats\\dnssec.js","original":{"line":145,"column":0},"generated":{"line":146,"column":0}},{"source":"node_modules\\sshpk\\lib\\formats\\dnssec.js","original":{"line":146,"column":0},"generated":{"line":147,"column":0}},{"source":"node_modules\\sshpk\\lib\\formats\\dnssec.js","original":{"line":147,"column":0},"generated":{"line":148,"column":0}},{"source":"node_modules\\sshpk\\lib\\formats\\dnssec.js","original":{"line":148,"column":0},"generated":{"line":149,"column":0}},{"source":"node_modules\\sshpk\\lib\\formats\\dnssec.js","original":{"line":149,"column":0},"generated":{"line":150,"column":0}},{"source":"node_modules\\sshpk\\lib\\formats\\dnssec.js","original":{"line":150,"column":0},"generated":{"line":151,"column":0}},{"source":"node_modules\\sshpk\\lib\\formats\\dnssec.js","original":{"line":151,"column":0},"generated":{"line":152,"column":0}},{"source":"node_modules\\sshpk\\lib\\formats\\dnssec.js","original":{"line":152,"column":0},"generated":{"line":153,"column":0}},{"source":"node_modules\\sshpk\\lib\\formats\\dnssec.js","original":{"line":153,"column":0},"generated":{"line":154,"column":0}},{"source":"node_modules\\sshpk\\lib\\formats\\dnssec.js","original":{"line":154,"column":0},"generated":{"line":155,"column":0}},{"source":"node_modules\\sshpk\\lib\\formats\\dnssec.js","original":{"line":155,"column":0},"generated":{"line":156,"column":0}},{"source":"node_modules\\sshpk\\lib\\formats\\dnssec.js","original":{"line":156,"column":0},"generated":{"line":157,"column":0}},{"source":"node_modules\\sshpk\\lib\\formats\\dnssec.js","original":{"line":157,"column":0},"generated":{"line":158,"column":0}},{"source":"node_modules\\sshpk\\lib\\formats\\dnssec.js","original":{"line":158,"column":0},"generated":{"line":159,"column":0}},{"source":"node_modules\\sshpk\\lib\\formats\\dnssec.js","original":{"line":159,"column":0},"generated":{"line":160,"column":0}},{"source":"node_modules\\sshpk\\lib\\formats\\dnssec.js","original":{"line":160,"column":0},"generated":{"line":161,"column":0}},{"source":"node_modules\\sshpk\\lib\\formats\\dnssec.js","original":{"line":161,"column":0},"generated":{"line":162,"column":0}},{"source":"node_modules\\sshpk\\lib\\formats\\dnssec.js","original":{"line":162,"column":0},"generated":{"line":163,"column":0}},{"source":"node_modules\\sshpk\\lib\\formats\\dnssec.js","original":{"line":163,"column":0},"generated":{"line":164,"column":0}},{"source":"node_modules\\sshpk\\lib\\formats\\dnssec.js","original":{"line":164,"column":0},"generated":{"line":165,"column":0}},{"source":"node_modules\\sshpk\\lib\\formats\\dnssec.js","original":{"line":165,"column":0},"generated":{"line":166,"column":0}},{"source":"node_modules\\sshpk\\lib\\formats\\dnssec.js","original":{"line":166,"column":0},"generated":{"line":167,"column":0}},{"source":"node_modules\\sshpk\\lib\\formats\\dnssec.js","original":{"line":167,"column":0},"generated":{"line":168,"column":0}},{"source":"node_modules\\sshpk\\lib\\formats\\dnssec.js","original":{"line":168,"column":0},"generated":{"line":169,"column":0}},{"source":"node_modules\\sshpk\\lib\\formats\\dnssec.js","original":{"line":169,"column":0},"generated":{"line":170,"column":0}},{"source":"node_modules\\sshpk\\lib\\formats\\dnssec.js","original":{"line":170,"column":0},"generated":{"line":171,"column":0}},{"source":"node_modules\\sshpk\\lib\\formats\\dnssec.js","original":{"line":171,"column":0},"generated":{"line":172,"column":0}},{"source":"node_modules\\sshpk\\lib\\formats\\dnssec.js","original":{"line":172,"column":0},"generated":{"line":173,"column":0}},{"source":"node_modules\\sshpk\\lib\\formats\\dnssec.js","original":{"line":173,"column":0},"generated":{"line":174,"column":0}},{"source":"node_modules\\sshpk\\lib\\formats\\dnssec.js","original":{"line":174,"column":0},"generated":{"line":175,"column":0}},{"source":"node_modules\\sshpk\\lib\\formats\\dnssec.js","original":{"line":175,"column":0},"generated":{"line":176,"column":0}},{"source":"node_modules\\sshpk\\lib\\formats\\dnssec.js","original":{"line":176,"column":0},"generated":{"line":177,"column":0}},{"source":"node_modules\\sshpk\\lib\\formats\\dnssec.js","original":{"line":177,"column":0},"generated":{"line":178,"column":0}},{"source":"node_modules\\sshpk\\lib\\formats\\dnssec.js","original":{"line":178,"column":0},"generated":{"line":179,"column":0}},{"source":"node_modules\\sshpk\\lib\\formats\\dnssec.js","original":{"line":179,"column":0},"generated":{"line":180,"column":0}},{"source":"node_modules\\sshpk\\lib\\formats\\dnssec.js","original":{"line":180,"column":0},"generated":{"line":181,"column":0}},{"source":"node_modules\\sshpk\\lib\\formats\\dnssec.js","original":{"line":181,"column":0},"generated":{"line":182,"column":0}},{"source":"node_modules\\sshpk\\lib\\formats\\dnssec.js","original":{"line":182,"column":0},"generated":{"line":183,"column":0}},{"source":"node_modules\\sshpk\\lib\\formats\\dnssec.js","original":{"line":183,"column":0},"generated":{"line":184,"column":0}},{"source":"node_modules\\sshpk\\lib\\formats\\dnssec.js","original":{"line":184,"column":0},"generated":{"line":185,"column":0}},{"source":"node_modules\\sshpk\\lib\\formats\\dnssec.js","original":{"line":185,"column":0},"generated":{"line":186,"column":0}},{"source":"node_modules\\sshpk\\lib\\formats\\dnssec.js","original":{"line":186,"column":0},"generated":{"line":187,"column":0}},{"source":"node_modules\\sshpk\\lib\\formats\\dnssec.js","original":{"line":187,"column":0},"generated":{"line":188,"column":0}},{"source":"node_modules\\sshpk\\lib\\formats\\dnssec.js","original":{"line":188,"column":0},"generated":{"line":189,"column":0}},{"source":"node_modules\\sshpk\\lib\\formats\\dnssec.js","original":{"line":189,"column":0},"generated":{"line":190,"column":0}},{"source":"node_modules\\sshpk\\lib\\formats\\dnssec.js","original":{"line":190,"column":0},"generated":{"line":191,"column":0}},{"source":"node_modules\\sshpk\\lib\\formats\\dnssec.js","original":{"line":191,"column":0},"generated":{"line":192,"column":0}},{"source":"node_modules\\sshpk\\lib\\formats\\dnssec.js","original":{"line":192,"column":0},"generated":{"line":193,"column":0}},{"source":"node_modules\\sshpk\\lib\\formats\\dnssec.js","original":{"line":193,"column":0},"generated":{"line":194,"column":0}},{"source":"node_modules\\sshpk\\lib\\formats\\dnssec.js","original":{"line":194,"column":0},"generated":{"line":195,"column":0}},{"source":"node_modules\\sshpk\\lib\\formats\\dnssec.js","original":{"line":195,"column":0},"generated":{"line":196,"column":0}},{"source":"node_modules\\sshpk\\lib\\formats\\dnssec.js","original":{"line":196,"column":0},"generated":{"line":197,"column":0}},{"source":"node_modules\\sshpk\\lib\\formats\\dnssec.js","original":{"line":197,"column":0},"generated":{"line":198,"column":0}},{"source":"node_modules\\sshpk\\lib\\formats\\dnssec.js","original":{"line":198,"column":0},"generated":{"line":199,"column":0}},{"source":"node_modules\\sshpk\\lib\\formats\\dnssec.js","original":{"line":199,"column":0},"generated":{"line":200,"column":0}},{"source":"node_modules\\sshpk\\lib\\formats\\dnssec.js","original":{"line":200,"column":0},"generated":{"line":201,"column":0}},{"source":"node_modules\\sshpk\\lib\\formats\\dnssec.js","original":{"line":201,"column":0},"generated":{"line":202,"column":0}},{"source":"node_modules\\sshpk\\lib\\formats\\dnssec.js","original":{"line":202,"column":0},"generated":{"line":203,"column":0}},{"source":"node_modules\\sshpk\\lib\\formats\\dnssec.js","original":{"line":203,"column":0},"generated":{"line":204,"column":0}},{"source":"node_modules\\sshpk\\lib\\formats\\dnssec.js","original":{"line":204,"column":0},"generated":{"line":205,"column":0}},{"source":"node_modules\\sshpk\\lib\\formats\\dnssec.js","original":{"line":205,"column":0},"generated":{"line":206,"column":0}},{"source":"node_modules\\sshpk\\lib\\formats\\dnssec.js","original":{"line":206,"column":0},"generated":{"line":207,"column":0}},{"source":"node_modules\\sshpk\\lib\\formats\\dnssec.js","original":{"line":207,"column":0},"generated":{"line":208,"column":0}},{"source":"node_modules\\sshpk\\lib\\formats\\dnssec.js","original":{"line":208,"column":0},"generated":{"line":209,"column":0}},{"source":"node_modules\\sshpk\\lib\\formats\\dnssec.js","original":{"line":209,"column":0},"generated":{"line":210,"column":0}},{"source":"node_modules\\sshpk\\lib\\formats\\dnssec.js","original":{"line":210,"column":0},"generated":{"line":211,"column":0}},{"source":"node_modules\\sshpk\\lib\\formats\\dnssec.js","original":{"line":211,"column":0},"generated":{"line":212,"column":0}},{"source":"node_modules\\sshpk\\lib\\formats\\dnssec.js","original":{"line":212,"column":0},"generated":{"line":213,"column":0}},{"source":"node_modules\\sshpk\\lib\\formats\\dnssec.js","original":{"line":213,"column":0},"generated":{"line":214,"column":0}},{"source":"node_modules\\sshpk\\lib\\formats\\dnssec.js","original":{"line":214,"column":0},"generated":{"line":215,"column":0}},{"source":"node_modules\\sshpk\\lib\\formats\\dnssec.js","original":{"line":215,"column":0},"generated":{"line":216,"column":0}},{"source":"node_modules\\sshpk\\lib\\formats\\dnssec.js","original":{"line":216,"column":0},"generated":{"line":217,"column":0}},{"source":"node_modules\\sshpk\\lib\\formats\\dnssec.js","original":{"line":217,"column":0},"generated":{"line":218,"column":0}},{"source":"node_modules\\sshpk\\lib\\formats\\dnssec.js","original":{"line":218,"column":0},"generated":{"line":219,"column":0}},{"source":"node_modules\\sshpk\\lib\\formats\\dnssec.js","original":{"line":219,"column":0},"generated":{"line":220,"column":0}},{"source":"node_modules\\sshpk\\lib\\formats\\dnssec.js","original":{"line":220,"column":0},"generated":{"line":221,"column":0}},{"source":"node_modules\\sshpk\\lib\\formats\\dnssec.js","original":{"line":221,"column":0},"generated":{"line":222,"column":0}},{"source":"node_modules\\sshpk\\lib\\formats\\dnssec.js","original":{"line":222,"column":0},"generated":{"line":223,"column":0}},{"source":"node_modules\\sshpk\\lib\\formats\\dnssec.js","original":{"line":223,"column":0},"generated":{"line":224,"column":0}},{"source":"node_modules\\sshpk\\lib\\formats\\dnssec.js","original":{"line":224,"column":0},"generated":{"line":225,"column":0}},{"source":"node_modules\\sshpk\\lib\\formats\\dnssec.js","original":{"line":225,"column":0},"generated":{"line":226,"column":0}},{"source":"node_modules\\sshpk\\lib\\formats\\dnssec.js","original":{"line":226,"column":0},"generated":{"line":227,"column":0}},{"source":"node_modules\\sshpk\\lib\\formats\\dnssec.js","original":{"line":227,"column":0},"generated":{"line":228,"column":0}},{"source":"node_modules\\sshpk\\lib\\formats\\dnssec.js","original":{"line":228,"column":0},"generated":{"line":229,"column":0}},{"source":"node_modules\\sshpk\\lib\\formats\\dnssec.js","original":{"line":229,"column":0},"generated":{"line":230,"column":0}},{"source":"node_modules\\sshpk\\lib\\formats\\dnssec.js","original":{"line":230,"column":0},"generated":{"line":231,"column":0}},{"source":"node_modules\\sshpk\\lib\\formats\\dnssec.js","original":{"line":231,"column":0},"generated":{"line":232,"column":0}},{"source":"node_modules\\sshpk\\lib\\formats\\dnssec.js","original":{"line":232,"column":0},"generated":{"line":233,"column":0}},{"source":"node_modules\\sshpk\\lib\\formats\\dnssec.js","original":{"line":233,"column":0},"generated":{"line":234,"column":0}},{"source":"node_modules\\sshpk\\lib\\formats\\dnssec.js","original":{"line":234,"column":0},"generated":{"line":235,"column":0}},{"source":"node_modules\\sshpk\\lib\\formats\\dnssec.js","original":{"line":235,"column":0},"generated":{"line":236,"column":0}},{"source":"node_modules\\sshpk\\lib\\formats\\dnssec.js","original":{"line":236,"column":0},"generated":{"line":237,"column":0}},{"source":"node_modules\\sshpk\\lib\\formats\\dnssec.js","original":{"line":237,"column":0},"generated":{"line":238,"column":0}},{"source":"node_modules\\sshpk\\lib\\formats\\dnssec.js","original":{"line":238,"column":0},"generated":{"line":239,"column":0}},{"source":"node_modules\\sshpk\\lib\\formats\\dnssec.js","original":{"line":239,"column":0},"generated":{"line":240,"column":0}},{"source":"node_modules\\sshpk\\lib\\formats\\dnssec.js","original":{"line":240,"column":0},"generated":{"line":241,"column":0}},{"source":"node_modules\\sshpk\\lib\\formats\\dnssec.js","original":{"line":241,"column":0},"generated":{"line":242,"column":0}},{"source":"node_modules\\sshpk\\lib\\formats\\dnssec.js","original":{"line":242,"column":0},"generated":{"line":243,"column":0}},{"source":"node_modules\\sshpk\\lib\\formats\\dnssec.js","original":{"line":243,"column":0},"generated":{"line":244,"column":0}},{"source":"node_modules\\sshpk\\lib\\formats\\dnssec.js","original":{"line":244,"column":0},"generated":{"line":245,"column":0}},{"source":"node_modules\\sshpk\\lib\\formats\\dnssec.js","original":{"line":245,"column":0},"generated":{"line":246,"column":0}},{"source":"node_modules\\sshpk\\lib\\formats\\dnssec.js","original":{"line":246,"column":0},"generated":{"line":247,"column":0}},{"source":"node_modules\\sshpk\\lib\\formats\\dnssec.js","original":{"line":247,"column":0},"generated":{"line":248,"column":0}},{"source":"node_modules\\sshpk\\lib\\formats\\dnssec.js","original":{"line":248,"column":0},"generated":{"line":249,"column":0}},{"source":"node_modules\\sshpk\\lib\\formats\\dnssec.js","original":{"line":249,"column":0},"generated":{"line":250,"column":0}},{"source":"node_modules\\sshpk\\lib\\formats\\dnssec.js","original":{"line":250,"column":0},"generated":{"line":251,"column":0}},{"source":"node_modules\\sshpk\\lib\\formats\\dnssec.js","original":{"line":251,"column":0},"generated":{"line":252,"column":0}},{"source":"node_modules\\sshpk\\lib\\formats\\dnssec.js","original":{"line":252,"column":0},"generated":{"line":253,"column":0}},{"source":"node_modules\\sshpk\\lib\\formats\\dnssec.js","original":{"line":253,"column":0},"generated":{"line":254,"column":0}},{"source":"node_modules\\sshpk\\lib\\formats\\dnssec.js","original":{"line":254,"column":0},"generated":{"line":255,"column":0}},{"source":"node_modules\\sshpk\\lib\\formats\\dnssec.js","original":{"line":255,"column":0},"generated":{"line":256,"column":0}},{"source":"node_modules\\sshpk\\lib\\formats\\dnssec.js","original":{"line":256,"column":0},"generated":{"line":257,"column":0}},{"source":"node_modules\\sshpk\\lib\\formats\\dnssec.js","original":{"line":257,"column":0},"generated":{"line":258,"column":0}},{"source":"node_modules\\sshpk\\lib\\formats\\dnssec.js","original":{"line":258,"column":0},"generated":{"line":259,"column":0}},{"source":"node_modules\\sshpk\\lib\\formats\\dnssec.js","original":{"line":259,"column":0},"generated":{"line":260,"column":0}},{"source":"node_modules\\sshpk\\lib\\formats\\dnssec.js","original":{"line":260,"column":0},"generated":{"line":261,"column":0}},{"source":"node_modules\\sshpk\\lib\\formats\\dnssec.js","original":{"line":261,"column":0},"generated":{"line":262,"column":0}},{"source":"node_modules\\sshpk\\lib\\formats\\dnssec.js","original":{"line":262,"column":0},"generated":{"line":263,"column":0}},{"source":"node_modules\\sshpk\\lib\\formats\\dnssec.js","original":{"line":263,"column":0},"generated":{"line":264,"column":0}},{"source":"node_modules\\sshpk\\lib\\formats\\dnssec.js","original":{"line":264,"column":0},"generated":{"line":265,"column":0}},{"source":"node_modules\\sshpk\\lib\\formats\\dnssec.js","original":{"line":265,"column":0},"generated":{"line":266,"column":0}},{"source":"node_modules\\sshpk\\lib\\formats\\dnssec.js","original":{"line":266,"column":0},"generated":{"line":267,"column":0}},{"source":"node_modules\\sshpk\\lib\\formats\\dnssec.js","original":{"line":267,"column":0},"generated":{"line":268,"column":0}},{"source":"node_modules\\sshpk\\lib\\formats\\dnssec.js","original":{"line":268,"column":0},"generated":{"line":269,"column":0}},{"source":"node_modules\\sshpk\\lib\\formats\\dnssec.js","original":{"line":269,"column":0},"generated":{"line":270,"column":0}},{"source":"node_modules\\sshpk\\lib\\formats\\dnssec.js","original":{"line":270,"column":0},"generated":{"line":271,"column":0}},{"source":"node_modules\\sshpk\\lib\\formats\\dnssec.js","original":{"line":271,"column":0},"generated":{"line":272,"column":0}},{"source":"node_modules\\sshpk\\lib\\formats\\dnssec.js","original":{"line":272,"column":0},"generated":{"line":273,"column":0}},{"source":"node_modules\\sshpk\\lib\\formats\\dnssec.js","original":{"line":273,"column":0},"generated":{"line":274,"column":0}},{"source":"node_modules\\sshpk\\lib\\formats\\dnssec.js","original":{"line":274,"column":0},"generated":{"line":275,"column":0}},{"source":"node_modules\\sshpk\\lib\\formats\\dnssec.js","original":{"line":275,"column":0},"generated":{"line":276,"column":0}},{"source":"node_modules\\sshpk\\lib\\formats\\dnssec.js","original":{"line":276,"column":0},"generated":{"line":277,"column":0}},{"source":"node_modules\\sshpk\\lib\\formats\\dnssec.js","original":{"line":277,"column":0},"generated":{"line":278,"column":0}},{"source":"node_modules\\sshpk\\lib\\formats\\dnssec.js","original":{"line":278,"column":0},"generated":{"line":279,"column":0}},{"source":"node_modules\\sshpk\\lib\\formats\\dnssec.js","original":{"line":279,"column":0},"generated":{"line":280,"column":0}},{"source":"node_modules\\sshpk\\lib\\formats\\dnssec.js","original":{"line":280,"column":0},"generated":{"line":281,"column":0}},{"source":"node_modules\\sshpk\\lib\\formats\\dnssec.js","original":{"line":281,"column":0},"generated":{"line":282,"column":0}},{"source":"node_modules\\sshpk\\lib\\formats\\dnssec.js","original":{"line":282,"column":0},"generated":{"line":283,"column":0}},{"source":"node_modules\\sshpk\\lib\\formats\\dnssec.js","original":{"line":283,"column":0},"generated":{"line":284,"column":0}},{"source":"node_modules\\sshpk\\lib\\formats\\dnssec.js","original":{"line":284,"column":0},"generated":{"line":285,"column":0}},{"source":"node_modules\\sshpk\\lib\\formats\\dnssec.js","original":{"line":285,"column":0},"generated":{"line":286,"column":0}},{"source":"node_modules\\sshpk\\lib\\formats\\dnssec.js","original":{"line":286,"column":0},"generated":{"line":287,"column":0}},{"source":"node_modules\\sshpk\\lib\\formats\\dnssec.js","original":{"line":287,"column":0},"generated":{"line":288,"column":0}}],"sources":{"node_modules\\sshpk\\lib\\formats\\dnssec.js":"// Copyright 2017 Joyent, Inc.\r\n\r\nmodule.exports = {\r\n\tread: read,\r\n\twrite: write\r\n};\r\n\r\nvar assert = require('assert-plus');\r\nvar Key = require('../key');\r\nvar PrivateKey = require('../private-key');\r\nvar utils = require('../utils');\r\nvar SSHBuffer = require('../ssh-buffer');\r\nvar Dhe = require('../dhe');\r\n\r\nvar supportedAlgos = {\r\n\t'rsa-sha1' : 5,\r\n\t'rsa-sha256' : 8,\r\n\t'rsa-sha512' : 10,\r\n\t'ecdsa-p256-sha256' : 13,\r\n\t'ecdsa-p384-sha384' : 14\r\n\t/*\r\n\t * ed25519 is hypothetically supported with id 15\r\n\t * but the common tools available don't appear to be\r\n\t * capable of generating/using ed25519 keys\r\n\t */\r\n};\r\n\r\nvar supportedAlgosById = {};\r\nObject.keys(supportedAlgos).forEach(function (k) {\r\n\tsupportedAlgosById[supportedAlgos[k]] = k.toUpperCase();\r\n});\r\n\r\nfunction read(buf, options) {\r\n\tif (typeof (buf) !== 'string') {\r\n\t\tassert.buffer(buf, 'buf');\r\n\t\tbuf = buf.toString('ascii');\r\n\t}\r\n\tvar lines = buf.split('\\n');\r\n\tif (lines[0].match(/^Private-key-format\\: v1/)) {\r\n\t\tvar algElems = lines[1].split(' ');\r\n\t\tvar algoNum = parseInt(algElems[1], 10);\r\n\t\tvar algoName = algElems[2];\r\n\t\tif (!supportedAlgosById[algoNum])\r\n\t\t\tthrow (new Error('Unsupported algorithm: ' + algoName));\r\n\t\treturn (readDNSSECPrivateKey(algoNum, lines.slice(2)));\r\n\t}\r\n\r\n\t// skip any comment-lines\r\n\tvar line = 0;\r\n\t/* JSSTYLED */\r\n\twhile (lines[line].match(/^\\;/))\r\n\t\tline++;\r\n\t// we should now have *one single* line left with our KEY on it.\r\n\tif ((lines[line].match(/\\. IN KEY /) ||\r\n\t    lines[line].match(/\\. IN DNSKEY /)) && lines[line+1].length === 0) {\r\n\t\treturn (readRFC3110(lines[line]));\r\n\t}\r\n\tthrow (new Error('Cannot parse dnssec key'));\r\n}\r\n\r\nfunction readRFC3110(keyString) {\r\n\tvar elems = keyString.split(' ');\r\n\t//unused var flags = parseInt(elems[3], 10);\r\n\t//unused var protocol = parseInt(elems[4], 10);\r\n\tvar algorithm = parseInt(elems[5], 10);\r\n\tif (!supportedAlgosById[algorithm])\r\n\t\tthrow (new Error('Unsupported algorithm: ' + algorithm));\r\n\tvar base64key = elems.slice(6, elems.length).join();\r\n\tvar keyBuffer = new Buffer(base64key, 'base64');\r\n\tif (supportedAlgosById[algorithm].match(/^RSA-/)) {\r\n\t\t// join the rest of the body into a single base64-blob\r\n\t\tvar publicExponentLen = keyBuffer.readUInt8(0);\r\n\t\tif (publicExponentLen != 3 && publicExponentLen != 1)\r\n\t\t\tthrow (new Error('Cannot parse dnssec key: ' +\r\n\t\t\t    'unsupported exponent length'));\r\n\r\n\t\tvar publicExponent = keyBuffer.slice(1, publicExponentLen+1);\r\n\t\tpublicExponent = utils.mpNormalize(publicExponent);\r\n\t\tvar modulus = keyBuffer.slice(1+publicExponentLen);\r\n\t\tmodulus = utils.mpNormalize(modulus);\r\n\t\t// now, make the key\r\n\t\tvar rsaKey = {\r\n\t\t\ttype: 'rsa',\r\n\t\t\tparts: []\r\n\t\t};\r\n\t\trsaKey.parts.push({ name: 'e', data: publicExponent});\r\n\t\trsaKey.parts.push({ name: 'n', data: modulus});\r\n\t\treturn (new Key(rsaKey));\r\n\t}\r\n\tif (supportedAlgosById[algorithm] === 'ECDSA-P384-SHA384' ||\r\n\t    supportedAlgosById[algorithm] === 'ECDSA-P256-SHA256') {\r\n\t\tvar curve = 'nistp384';\r\n\t\tvar size = 384;\r\n\t\tif (supportedAlgosById[algorithm].match(/^ECDSA-P256-SHA256/)) {\r\n\t\t\tcurve = 'nistp256';\r\n\t\t\tsize = 256;\r\n\t\t}\r\n\r\n\t\tvar ecdsaKey = {\r\n\t\t\ttype: 'ecdsa',\r\n\t\t\tcurve: curve,\r\n\t\t\tsize: size,\r\n\t\t\tparts: [\r\n\t\t\t\t{name: 'curve', data: new Buffer(curve) },\r\n\t\t\t\t{name: 'Q', data: utils.ecNormalize(keyBuffer) }\r\n\t\t\t]\r\n\t\t};\r\n\t\treturn (new Key(ecdsaKey));\r\n\t}\r\n\tthrow (new Error('Unsupported algorithm: ' +\r\n\t    supportedAlgosById[algorithm]));\r\n}\r\n\r\nfunction elementToBuf(e) {\r\n\treturn (new Buffer(e.split(' ')[1], 'base64'));\r\n}\r\n\r\nfunction readDNSSECRSAPrivateKey(elements) {\r\n\tvar rsaParams = {};\r\n\telements.forEach(function (element) {\r\n\t\tif (element.split(' ')[0] === 'Modulus:')\r\n\t\t\trsaParams['n'] = elementToBuf(element);\r\n\t\telse if (element.split(' ')[0] === 'PublicExponent:')\r\n\t\t\trsaParams['e'] = elementToBuf(element);\r\n\t\telse if (element.split(' ')[0] === 'PrivateExponent:')\r\n\t\t\trsaParams['d'] = elementToBuf(element);\r\n\t\telse if (element.split(' ')[0] === 'Prime1:')\r\n\t\t\trsaParams['p'] = elementToBuf(element);\r\n\t\telse if (element.split(' ')[0] === 'Prime2:')\r\n\t\t\trsaParams['q'] = elementToBuf(element);\r\n\t\telse if (element.split(' ')[0] === 'Exponent1:')\r\n\t\t\trsaParams['dmodp'] = elementToBuf(element);\r\n\t\telse if (element.split(' ')[0] === 'Exponent2:')\r\n\t\t\trsaParams['dmodq'] = elementToBuf(element);\r\n\t\telse if (element.split(' ')[0] === 'Coefficient:')\r\n\t\t\trsaParams['iqmp'] = elementToBuf(element);\r\n\t});\r\n\t// now, make the key\r\n\tvar key = {\r\n\t\ttype: 'rsa',\r\n\t\tparts: [\r\n\t\t\t{ name: 'e', data: utils.mpNormalize(rsaParams['e'])},\r\n\t\t\t{ name: 'n', data: utils.mpNormalize(rsaParams['n'])},\r\n\t\t\t{ name: 'd', data: utils.mpNormalize(rsaParams['d'])},\r\n\t\t\t{ name: 'p', data: utils.mpNormalize(rsaParams['p'])},\r\n\t\t\t{ name: 'q', data: utils.mpNormalize(rsaParams['q'])},\r\n\t\t\t{ name: 'dmodp',\r\n\t\t\t    data: utils.mpNormalize(rsaParams['dmodp'])},\r\n\t\t\t{ name: 'dmodq',\r\n\t\t\t    data: utils.mpNormalize(rsaParams['dmodq'])},\r\n\t\t\t{ name: 'iqmp',\r\n\t\t\t    data: utils.mpNormalize(rsaParams['iqmp'])}\r\n\t\t]\r\n\t};\r\n\treturn (new PrivateKey(key));\r\n}\r\n\r\nfunction readDNSSECPrivateKey(alg, elements) {\r\n\tif (supportedAlgosById[alg].match(/^RSA-/)) {\r\n\t\treturn (readDNSSECRSAPrivateKey(elements));\r\n\t}\r\n\tif (supportedAlgosById[alg] === 'ECDSA-P384-SHA384' ||\r\n\t    supportedAlgosById[alg] === 'ECDSA-P256-SHA256') {\r\n\t\tvar d = new Buffer(elements[0].split(' ')[1], 'base64');\r\n\t\tvar curve = 'nistp384';\r\n\t\tvar size = 384;\r\n\t\tif (supportedAlgosById[alg] === 'ECDSA-P256-SHA256') {\r\n\t\t\tcurve = 'nistp256';\r\n\t\t\tsize = 256;\r\n\t\t}\r\n\t\t// DNSSEC generates the public-key on the fly (go calculate it)\r\n\t\tvar publicKey = utils.publicFromPrivateECDSA(curve, d);\r\n\t\tvar Q = publicKey.part['Q'].data;\r\n\t\tvar ecdsaKey = {\r\n\t\t\ttype: 'ecdsa',\r\n\t\t\tcurve: curve,\r\n\t\t\tsize: size,\r\n\t\t\tparts: [\r\n\t\t\t\t{name: 'curve', data: new Buffer(curve) },\r\n\t\t\t\t{name: 'd', data: d },\r\n\t\t\t\t{name: 'Q', data: Q }\r\n\t\t\t]\r\n\t\t};\r\n\t\treturn (new PrivateKey(ecdsaKey));\r\n\t}\r\n\tthrow (new Error('Unsupported algorithm: ' + supportedAlgosById[alg]));\r\n}\r\n\r\nfunction dnssecTimestamp(date) {\r\n\tvar year = date.getFullYear() + ''; //stringify\r\n\tvar month = (date.getMonth() + 1);\r\n\tvar timestampStr = year + month + date.getUTCDate();\r\n\ttimestampStr += '' + date.getUTCHours() + date.getUTCMinutes();\r\n\ttimestampStr += date.getUTCSeconds();\r\n\treturn (timestampStr);\r\n}\r\n\r\nfunction rsaAlgFromOptions(opts) {\r\n\tif (!opts || !opts.hashAlgo || opts.hashAlgo === 'sha1')\r\n\t\treturn ('5 (RSASHA1)');\r\n\telse if (opts.hashAlgo === 'sha256')\r\n\t\treturn ('8 (RSASHA256)');\r\n\telse if (opts.hashAlgo === 'sha512')\r\n\t\treturn ('10 (RSASHA512)');\r\n\telse\r\n\t\tthrow (new Error('Unknown or unsupported hash: ' +\r\n\t\t    opts.hashAlgo));\r\n}\r\n\r\nfunction writeRSA(key, options) {\r\n\t// if we're missing parts, add them.\r\n\tif (!key.part.dmodp || !key.part.dmodq) {\r\n\t\tutils.addRSAMissing(key);\r\n\t}\r\n\r\n\tvar out = '';\r\n\tout += 'Private-key-format: v1.3\\n';\r\n\tout += 'Algorithm: ' + rsaAlgFromOptions(options) + '\\n';\r\n\tvar n = utils.mpDenormalize(key.part['n'].data);\r\n\tout += 'Modulus: ' + n.toString('base64') + '\\n';\r\n\tvar e = utils.mpDenormalize(key.part['e'].data);\r\n\tout += 'PublicExponent: ' + e.toString('base64') + '\\n';\r\n\tvar d = utils.mpDenormalize(key.part['d'].data);\r\n\tout += 'PrivateExponent: ' + d.toString('base64') + '\\n';\r\n\tvar p = utils.mpDenormalize(key.part['p'].data);\r\n\tout += 'Prime1: ' + p.toString('base64') + '\\n';\r\n\tvar q = utils.mpDenormalize(key.part['q'].data);\r\n\tout += 'Prime2: ' + q.toString('base64') + '\\n';\r\n\tvar dmodp = utils.mpDenormalize(key.part['dmodp'].data);\r\n\tout += 'Exponent1: ' + dmodp.toString('base64') + '\\n';\r\n\tvar dmodq = utils.mpDenormalize(key.part['dmodq'].data);\r\n\tout += 'Exponent2: ' + dmodq.toString('base64') + '\\n';\r\n\tvar iqmp = utils.mpDenormalize(key.part['iqmp'].data);\r\n\tout += 'Coefficient: ' + iqmp.toString('base64') + '\\n';\r\n\t// Assume that we're valid as-of now\r\n\tvar timestamp = new Date();\r\n\tout += 'Created: ' + dnssecTimestamp(timestamp) + '\\n';\r\n\tout += 'Publish: ' + dnssecTimestamp(timestamp) + '\\n';\r\n\tout += 'Activate: ' + dnssecTimestamp(timestamp) + '\\n';\r\n\treturn (new Buffer(out, 'ascii'));\r\n}\r\n\r\nfunction writeECDSA(key, options) {\r\n\tvar out = '';\r\n\tout += 'Private-key-format: v1.3\\n';\r\n\r\n\tif (key.curve === 'nistp256') {\r\n\t\tout += 'Algorithm: 13 (ECDSAP256SHA256)\\n';\r\n\t} else if (key.curve === 'nistp384') {\r\n\t\tout += 'Algorithm: 14 (ECDSAP384SHA384)\\n';\r\n\t} else {\r\n\t\tthrow (new Error('Unsupported curve'));\r\n\t}\r\n\tvar base64Key = key.part['d'].data.toString('base64');\r\n\tout += 'PrivateKey: ' + base64Key + '\\n';\r\n\r\n\t// Assume that we're valid as-of now\r\n\tvar timestamp = new Date();\r\n\tout += 'Created: ' + dnssecTimestamp(timestamp) + '\\n';\r\n\tout += 'Publish: ' + dnssecTimestamp(timestamp) + '\\n';\r\n\tout += 'Activate: ' + dnssecTimestamp(timestamp) + '\\n';\r\n\r\n\treturn (new Buffer(out, 'ascii'));\r\n}\r\n\r\nfunction write(key, options) {\r\n\tif (PrivateKey.isPrivateKey(key)) {\r\n\t\tif (key.type === 'rsa') {\r\n\t\t\treturn (writeRSA(key, options));\r\n\t\t} else if (key.type === 'ecdsa') {\r\n\t\t\treturn (writeECDSA(key, options));\r\n\t\t} else {\r\n\t\t\tthrow (new Error('Unsupported algorithm: ' + key.type));\r\n\t\t}\r\n\t} else if (Key.isKey(key)) {\r\n\t\t/*\r\n\t\t * RFC3110 requires a keyname, and a keytype, which we\r\n\t\t * don't really have a mechanism for specifying such\r\n\t\t * additional metadata.\r\n\t\t */\r\n\t\tthrow (new Error('Format \"dnssec\" only supports ' +\r\n\t\t    'writing private keys'));\r\n\t} else {\r\n\t\tthrow (new Error('key is not a Key or PrivateKey'));\r\n\t}\r\n}\r\n"},"lineCount":288}},"hash":"9a7efa2baf3445bc950bb4d6101c6915","cacheData":{"env":{}}}